pnno/__init__.py
pnno/anno/__init__.py
pnno/anno/base_anno.py
pnno/anno/build.py
pnno/anno/labelimg_anno.py
pnno/anno/lmdb.py
pnno/anno/pytorch_imagefolder.py
pnno/anno/registry.py
pnno/anno/tlt_anno.py
pnno/anno/visdrone_anno.py
pnno/anno/yolov5_anno.py
pnno/config/__init__.py
pnno/config/defaults.py
pnno/engine/__init__.py
pnno/engine/anno_processor.py
pnno/engine/defaults.py
pnno/engine/processor.py
pnno/tool/__init__.py
pnno/tool/cli.py
pnno/tool/show.py
pnno/tools/__init__.py
pnno/tools/cli.py
pnno/util/__init__.py
pnno/util/logger.py
pnno/util/misc.py
pnno/util/parse_voc_xml.py
pnno/util/registry.py
pnno/util/utility.py
pnno/utils/__init__.py
pnno/utils/logger.py
pnno/utils/misc.py
pnno/utils/parse_voc_xml.py
pnno/utils/registry.py
pnno/utils/utility.py
pnno-0.3.7.dist-info/LICENSE
pnno-0.3.7.dist-info/METADATA
pnno-0.3.7.dist-info/WHEEL
pnno-0.3.7.dist-info/entry_points.txt
pnno-0.3.7.dist-info/top_level.txt
pnno-0.3.7.dist-info/RECORD
