Metadata-Version: 2.1
Name: pnno
Version: 0.3.7
Summary: Script for annotation data processing
Home-page: https://github.com/zjykzj/pnno
Author: zj
Author-email: wy163zhuj@163.com
License: UNKNOWN
Platform: UNKNOWN
Classifier: Programming Language :: Python :: 3
Classifier: Operating System :: OS Independent
Classifier: License :: OSI Approved :: Apache Software License
Requires-Python: >=3.6
Requires-Dist: Pillow (>=8.1.0)
Requires-Dist: imageio (>=2.9.0)
Requires-Dist: lmdb (>=1.1.1)
Requires-Dist: numpy (>=1.19.5)
Requires-Dist: opencv-python (>=4.5.1.48)
Requires-Dist: torch (>=1.7.1)
Requires-Dist: torchvision (>=0.8.2)
Requires-Dist: tqdm (>=4.56.0)
Requires-Dist: xmltodict (>=0.12.0)
Requires-Dist: yacs (>=0.1.8)
